tum_scout_metadata/__init__.py
tum_scout_metadata/interfaces.py
tum_scout_metadata/py.typed
tum_scout_metadata/types.py
tum_scout_metadata-0.8.4.dist-info/METADATA
tum_scout_metadata-0.8.4.dist-info/WHEEL
tum_scout_metadata-0.8.4.dist-info/RECORD
