Metadata-Version: 2.4
Name: tum_scout_metadata
Version: 0.8.4
Summary: Single source of truth for ESM's SCOUT measurement logistics
Project-URL: repository, https://github.com/tum-esm/scout-metadata
Author-email: Daniel Kühbacher <daniel.kuehbacher@tum.de>, Felix Böhm <felix.boehm@tum.de>, Moritz Makowski <moritz.makowski@tum.de>
Requires-Python: <3.12,>=3.9
Requires-Dist: pendulum<3.0.0,>=2.1.2
Requires-Dist: pydantic<2.0.0,>=1.10.4
Requires-Dist: tum-esm-utils<2.0.0,>=1.2.1
